__init__.py
jumper/__init__.py
jumper/install.py
jumper/kernel.py
jumper/logo.py
jumper/perfdatahandler.py
jumper/userpersistence.py
jumper/visualization.py
jumper/multinode_monitor/abstract_monitor.py
jumper/multinode_monitor/slurm_monitor.py
parallel_marshall/__init__.py
parallel_marshall/balanced_distribution_iterator.py
parallel_marshall/parallel_marshall.py
perfmonitor/__init__.py
perfmonitor/__main__.py
jumper_kernel-1.1.1.dist-info/LICENSE
jumper_kernel-1.1.1.dist-info/METADATA
jumper_kernel-1.1.1.dist-info/WHEEL
jumper_kernel-1.1.1.dist-info/top_level.txt
jumper_kernel-1.1.1.dist-info/RECORD
