Metadata-Version: 2.1
Name: jumper-kernel
Version: 1.1.1
Summary: This is a Jupyter Python Kernel for performance engineering. Beside performance data as CPU, GPU, memory utilization it supports performance data recording with Score-P.
Author-email: Elias Werner <elias.werner@tu-dresden.de>
License: Copyright (c) 2022, Technische Universitaet Dresden, Germany, all rights reserved.
Project-URL: homepage, https://github.com/score-p/scorep_jupyter_kernel_python
Project-URL: repository, https://github.com/score-p/scorep_jupyter_kernel_python
Classifier: Programming Language :: Python :: 3
Requires-Python: >=3.8
License-File: LICENSE
Requires-Dist: ipykernel
Requires-Dist: ipywidgets
Requires-Dist: ipympl
Requires-Dist: jupyter-client
Requires-Dist: astunparse
Requires-Dist: dill
Requires-Dist: itables
Requires-Dist: matplotlib
Requires-Dist: pandas
Requires-Dist: pynvml
